setup.py
mallard/__init__.py
mallard.egg-info/PKG-INFO
mallard.egg-info/SOURCES.txt
mallard.egg-info/dependency_links.txt
mallard.egg-info/requires.txt
mallard.egg-info/top_level.txt
mallard/examples/pushexample.py