Metadata-Version: 1.0
Name: mallard
Version: 1.0.0
Summary: Library to send events to ducksboard.com
Home-page: https://github.com/hamstah/mallard
Author: Nicolas Esteves
Author-email: hamstahguru@gmail.com
License: UNKNOWN
Platform: UNKNOWN
